pytorch_bayes/__init__.py
pytorch_bayes/distributions/__init__.py
pytorch_bayes/distributions/distribution.py
pytorch_bayes/distributions/prior.py
pytorch_bayes/distributions/variational_posterior.py
pytorch_bayes/nn/__init__.py
pytorch_bayes/nn/bayesian_module.py
pytorch_bayes/nn/utils.py
pytorch_bayes/nn/bayes_by_backprop/__init__.py
pytorch_bayes/nn/bayes_by_backprop/bayesian_linear.py
pytorch_bayes/nn/bayes_by_backprop/bayesian_mlp.py
PyTorch_Bayes-0.0.3.dist-info/METADATA
PyTorch_Bayes-0.0.3.dist-info/WHEEL
PyTorch_Bayes-0.0.3.dist-info/top_level.txt
PyTorch_Bayes-0.0.3.dist-info/RECORD
